{
    "date": "2024-04-13",
    "sample_bank": "streamed_audio",
    "envelopes": {
        "envelope": [
            [
                6,
                32700
            ],
            [
                6,
                32700
            ],
            [
                32700,
                29430
            ],
            "hang"
        ]
    },
    "instruments": {
        "channel_1": {
            "release_rate": 10,
            "envelope": "envelope",
            "sound": "omori_welcome_again"
        }
    },
    "instrument_list": [
        "channel_1"
    ]
}